vllama/__init__.py
vllama/cli.py
vllama/core.py
vllama/model_training.py
vllama/preprocess.py
vllama/remote.py
vllama/functions/__init__.py
vllama/functions/image3d/__init__.py
vllama/functions/image3d/image3d.py
vllama/functions/image3d/image3dRemote.py
vllama/functions/object_detection_video/__init__.py
vllama/functions/object_detection_video/object_detection_video.py
vllama/functions/video3d/__init__.py
vllama/functions/video3d/convert_mov_mp4.py
vllama/functions/video3d/video3dLocal.py
vllama/functions/video3d/video3dRemote.py
vllama/functions/video3d/video3dRemote2.py
vllama/functions/viewer3d/__init__.py
vllama/functions/viewer3d/viewer3d.py
vllama-1.8.0.dist-info/licenses/LICENSE
vllama-1.8.0.dist-info/METADATA
vllama-1.8.0.dist-info/WHEEL
vllama-1.8.0.dist-info/entry_points.txt
vllama-1.8.0.dist-info/top_level.txt
vllama-1.8.0.dist-info/RECORD
