Metadata-Version: 2.4
Name: vllama
Version: 1.8.0
Summary: Comprehensive CLI tool and VS Code extension for vision models, AutoML, and local LLMs
Home-page: https://github.com/DayInfinity/Vllama
Author: Gopu Manvith
Author-email: Gopu Manvith <manvithgopu1394@gmail.com>
License: Apache-2.0
Project-URL: Homepage, https://github.com/DayInfinity/Vllama
Project-URL: Documentation, https://github.com/DayInfinity/Vllama#readme
Project-URL: Repository, https://github.com/DayInfinity/Vllama
Project-URL: Issues, https://github.com/DayInfinity/Vllama/issues
Project-URL: Changelog, https://github.com/DayInfinity/Vllama/blob/main/CHANGELOG.md
Keywords: machine-learning,deep-learning,computer-vision,stable-diffusion,automl,data-preprocessing,llm,vscode-extension,kaggle,gpu,imageio-ffmpeg
Classifier: Development Status :: 4 - Beta
Classifier: Intended Audience :: Developers
Classifier: Intended Audience :: Science/Research
Classifier: License :: OSI Approved :: Apache Software License
Classifier: Programming Language :: Python :: 3
Classifier: Programming Language :: Python :: 3.8
Classifier: Programming Language :: Python :: 3.9
Classifier: Programming Language :: Python :: 3.10
Classifier: Programming Language :: Python :: 3.11
Classifier: Topic :: Scientific/Engineering :: Artificial Intelligence
Classifier: Topic :: Software Development :: Libraries :: Python Modules
Requires-Python: >=3.8
License-File: LICENSE
Requires-Dist: torch>=2.0.0
Requires-Dist: diffusers>=0.20.0
Requires-Dist: transformers>=4.30.0
Requires-Dist: accelerate>=0.20.0
Requires-Dist: protobuf>=3.20.0
Requires-Dist: kaggle>=1.5.0
Requires-Dist: pandas>=1.5.0
Requires-Dist: numpy>=1.23.0
Requires-Dist: matplotlib>=3.5.0
Requires-Dist: seaborn>=0.12.0
Requires-Dist: scikit-learn>=1.2.0
Requires-Dist: xgboost>=1.7.6
Requires-Dist: lightgbm>=3.3.5
Requires-Dist: catboost>=1.2.1
Requires-Dist: joblib>=1.2.0
Requires-Dist: imageio>=2.31.0
Requires-Dist: build==1.3.0
Requires-Dist: twine
Requires-Dist: flask
Requires-Dist: pyttsx3
Requires-Dist: SpeechRecognition
Requires-Dist: pyaudio
Requires-Dist: soundfile
Requires-Dist: regex
Requires-Dist: ultralytics
Requires-Dist: opencv-python
Requires-Dist: requests
Requires-Dist: lap
Dynamic: author
Dynamic: home-page
Dynamic: license-file
Dynamic: requires-python
